[
  {
    "event-name": "Web Designing Workshop",
    "date": "10, 11 January 2019",
    "year": "2019",
    "time": "10 a.m. to 4 p.m.",
    "link": "",
    "mode": "",
    "category": "",
    "organizers": "CSI NMAMIT",
    "description": "CSI brings to you another workshop this week on Web Designing. Web development is a very enticing field to work on, and we're here to help you figure out the basics of it. Come join us to learn about all the key aspects of an amazing web design. Resource person: Hashif TP, Founder and CEO, A S Designs Pvt Ltd. Attendance benefits shall be provided to all the participants. Students are required to bring their own laptops, with Adobe Dreamweaver pre-installed. Installation can be done in college with the guidance of us before the session starts. Make the best out of this opportunity and have a sneak peek into the most important part of web navigation.",
    "venue": "Shambhavi Hall",
    "registration-fees": "Rs.110",
    "contact-person": ["Rahul S"]
  },
  {
    "event-name": "Minute to Win It",
    "date": "20 February 2019",
    "year": "2019",
    "time": "1:30 p.m.",
    "link": "",
    "mode": "",
    "category": "",
    "organizers": "CSI",
    "description": "Come participate in CSI's event, Minute to Win It. Arrive in teams of 2 and power through 3 rounds of exciting games to claim the title of the ultimate champion. Winners shall be awarded exciting cash prizes. Here's to hoping we see you all in high spirits this Wednesday.",
    "venue": "LH 110, 112",
    "registration-fees": "Rs. 20/- per team",
    "contact-persons": [
      {
        "name": "Kavya N",
        "contact-number": "+916361363150"
      },
      {
        "name": "Navya",
        "contact-number": "+919535045494"
      },
      {
        "name": "Deeksha",
        "contact-number": "+919686085503"
      },
      {
        "name": "Rohit J",
        "contact-number": "+918904835012"
      }
    ]
  }
]
